pyASDReader/__init__.py
pyASDReader/_version.py
pyASDReader/asd_file_reader.py
pyASDReader/constant.py
pyASDReader/file_attributes.py
pyASDReader/logger_setup.py
pyasdreader-1.2.3.dist-info/licenses/LICENSE
pyasdreader-1.2.3.dist-info/METADATA
pyasdreader-1.2.3.dist-info/WHEEL
pyasdreader-1.2.3.dist-info/top_level.txt
pyasdreader-1.2.3.dist-info/RECORD
