Metadata-Version: 2.4
Name: pyASDReader
Version: 1.2.3
Summary: A Python library for reading and parsing all versions of ASD binary spectral files
Author-email: Kai Cao <caokai_cgs@163.com>
Maintainer-email: Kai Cao <caokai_cgs@163.com>
License: MIT License
Project-URL: Homepage, https://github.com/KaiTastic/pyASDReader
Project-URL: Documentation, https://github.com/KaiTastic/pyASDReader#readme
Project-URL: Repository, https://github.com/KaiTastic/pyASDReader
Project-URL: Source, https://github.com/KaiTastic/pyASDReader
Project-URL: Issues, https://github.com/KaiTastic/pyASDReader/issues
Project-URL: Bug Reports, https://github.com/KaiTastic/pyASDReader/issues
Project-URL: Changelog, https://github.com/KaiTastic/pyASDReader/blob/main/CHANGELOG.md
Project-URL: PyPI, https://pypi.org/project/pyASDReader/
Keywords: ASD,spectral files,spectroradiometer,remote sensing
Classifier: Development Status :: 5 - Production/Stable
Classifier: Intended Audience :: Science/Research
Classifier: Topic :: Scientific/Engineering :: Information Analysis
Classifier: Programming Language :: Python :: 3
Classifier: Programming Language :: Python :: 3.8
Classifier: Programming Language :: Python :: 3.9
Classifier: Programming Language :: Python :: 3.10
Classifier: Programming Language :: Python :: 3.11
Classifier: Programming Language :: Python :: 3.12
Classifier: License :: OSI Approved :: MIT License
Classifier: Operating System :: OS Independent
Requires-Python: >=3.8
License-File: LICENSE
Requires-Dist: numpy>=1.20.0
Provides-Extra: dev
Requires-Dist: pytest>=6.0.0; extra == "dev"
Requires-Dist: pytest-cov>=2.10.0; extra == "dev"
Requires-Dist: pytest-html>=3.0.0; extra == "dev"
Requires-Dist: coverage>=5.0.0; extra == "dev"
Requires-Dist: flake8>=3.8.0; extra == "dev"
Requires-Dist: black>=21.0.0; extra == "dev"
Requires-Dist: isort>=5.0.0; extra == "dev"
Requires-Dist: build>=0.7.0; extra == "dev"
Requires-Dist: twine>=3.0.0; extra == "dev"
Requires-Dist: pre-commit>=2.15.0; extra == "dev"
Requires-Dist: tox>=3.20.0; extra == "dev"
Provides-Extra: docs
Requires-Dist: sphinx>=4.0.0; extra == "docs"
Requires-Dist: sphinx-rtd-theme>=1.0.0; extra == "docs"
Provides-Extra: all
Requires-Dist: pytest>=6.0.0; extra == "all"
Requires-Dist: pytest-cov>=2.10.0; extra == "all"
Requires-Dist: pytest-html>=3.0.0; extra == "all"
Requires-Dist: coverage>=5.0.0; extra == "all"
Requires-Dist: flake8>=3.8.0; extra == "all"
Requires-Dist: black>=21.0.0; extra == "all"
Requires-Dist: isort>=5.0.0; extra == "all"
Requires-Dist: build>=0.7.0; extra == "all"
Requires-Dist: twine>=3.0.0; extra == "all"
Requires-Dist: pre-commit>=2.15.0; extra == "all"
Requires-Dist: tox>=3.20.0; extra == "all"
Requires-Dist: sphinx>=4.0.0; extra == "all"
Requires-Dist: sphinx-rtd-theme>=1.0.0; extra == "all"
Dynamic: license-file
